universal_api_client/__init__.py
universal_api_client/client.py
universal_api_client/request.py
universal_api_client-0.2.0.dist-info/LICENSE
universal_api_client-0.2.0.dist-info/METADATA
universal_api_client-0.2.0.dist-info/WHEEL
universal_api_client-0.2.0.dist-info/top_level.txt
universal_api_client-0.2.0.dist-info/RECORD
