Metadata-Version: 2.1
Name: universal-api-client
Version: 0.2.0
Summary: А library for a REST API client that works with any API that follows somewhat the REST standard.
Home-page: https://github.com/jorgii/universal-api-client
Author: George Goranov
Author-email: g.p.goranov@gmail.com
License: MIT
Platform: UNKNOWN
Classifier: Development Status :: 3 - Alpha
Classifier: Intended Audience :: Developers
Classifier: Programming Language :: Python
Classifier: Programming Language :: Python :: 3.6
Classifier: Programming Language :: Python :: 3.7
Classifier: Programming Language :: Python :: 3.8
Classifier: License :: OSI Approved :: MIT License
Classifier: Operating System :: OS Independent
Requires-Dist: requests (<=3,>=2)
